sentry_kafka_schemas/__init__.py
sentry_kafka_schemas/py.typed
sentry_kafka_schemas/sentry_kafka_schemas.py
sentry_kafka_schemas/types.py
sentry_kafka_schemas/codecs/__init__.py
sentry_kafka_schemas/codecs/json.py
sentry_kafka_schemas/codecs/msgpack.py
sentry_kafka_schemas/codecs/protobuf.py
sentry_kafka_schemas/examples/any/garbage1.json
sentry_kafka_schemas/examples/buffered-segments/1/basic_buffered_segment.json
sentry_kafka_schemas/examples/events/1/end-delete-groups.json
sentry_kafka_schemas/examples/events/1/end-delete-tag.json
sentry_kafka_schemas/examples/events/1/end-merge.json
sentry_kafka_schemas/examples/events/1/end-unmerge-with-transaction.json
sentry_kafka_schemas/examples/events/1/end-unmerge.json
sentry_kafka_schemas/examples/events/1/error-with-null-threads.json
sentry_kafka_schemas/examples/events/1/error-with-null-values-threads.json
sentry_kafka_schemas/examples/events/1/error-with-threads.json
sentry_kafka_schemas/examples/events/1/errors1.json
sentry_kafka_schemas/examples/events/1/exclude-groups.json
sentry_kafka_schemas/examples/events/1/null-tag-keys.json
sentry_kafka_schemas/examples/events/1/null-values.json
sentry_kafka_schemas/examples/events/1/replace-group.json
sentry_kafka_schemas/examples/events/1/sdk-info-java.json
sentry_kafka_schemas/examples/events/1/start-delete-groups.json
sentry_kafka_schemas/examples/events/1/start-merge.json
sentry_kafka_schemas/examples/events/1/tombstone-events-no-datetime.json
sentry_kafka_schemas/examples/events/1/tombstone-events-timestamp.json
sentry_kafka_schemas/examples/events/1/tombstone-events.json
sentry_kafka_schemas/examples/events/1/weird-transaction-source.json
sentry_kafka_schemas/examples/generic-events/1/generic.json
sentry_kafka_schemas/examples/generic-events/1/insert.json
sentry_kafka_schemas/examples/group-attributes/1/assignee_changed.json
sentry_kafka_schemas/examples/group-attributes/1/group_created.json
sentry_kafka_schemas/examples/group-attributes/1/group_deleted.json
sentry_kafka_schemas-2.1.19.dist-info/licenses/LICENSE.md
sentry_kafka_schemas-2.1.19.dist-info/METADATA
sentry_kafka_schemas-2.1.19.dist-info/WHEEL
sentry_kafka_schemas-2.1.19.dist-info/top_level.txt
sentry_kafka_schemas-2.1.19.dist-info/RECORD
